privalyse_mask/__init__.py
privalyse_mask/core.py
privalyse_mask/recognizers.py
privalyse_mask/utils.py
privalyse_mask-0.1.1.dist-info/METADATA
privalyse_mask-0.1.1.dist-info/WHEEL
privalyse_mask-0.1.1.dist-info/licenses/LICENSE
privalyse_mask-0.1.1.dist-info/RECORD
