Metadata-Version: 2.4
Name: privalyse-mask
Version: 0.1.1
Summary: Advanced PII pseudonymization for LLM context preservation.
Project-URL: Homepage, https://github.com/yourusername/privalyse-mask
Project-URL: Repository, https://github.com/yourusername/privalyse-mask
Author-email: Privalyse Team <hello@privalyse.ai>
License-Expression: MIT
License-File: LICENSE
Classifier: Development Status :: 3 - Alpha
Classifier: Intended Audience :: Developers
Classifier: License :: OSI Approved :: MIT License
Classifier: Programming Language :: Python :: 3
Classifier: Topic :: Scientific/Engineering :: Artificial Intelligence
Classifier: Topic :: Security
Requires-Python: >=3.8
Requires-Dist: dateparser>=1.1.0
Requires-Dist: faker>=19.0.0
Requires-Dist: presidio-analyzer>=2.2.0
Requires-Dist: presidio-anonymizer>=2.2.0
Requires-Dist: spacy>=3.0.0
